fuseoverlayfs.py
fuse_overlayfs-0.1.0.dist-info/LICENSE
fuse_overlayfs-0.1.0.dist-info/METADATA
fuse_overlayfs-0.1.0.dist-info/WHEEL
fuse_overlayfs-0.1.0.dist-info/top_level.txt
fuse_overlayfs-0.1.0.dist-info/RECORD
