Metadata-Version: 2.1
Name: fuse-overlayfs
Version: 0.1.0
Summary: Use fuse-overlayfs to mount/unmount overlayfs in Python
Author: nukemiko
License: MIT License
Project-URL: Repository, https://github.com/nukemiko/python-fuse-overlayfs
Project-URL: Issues, https://github.com/nukemiko/python-fuse-overlayfs/issues
Project-URL: Changelog, https://github.com/nukemiko/python-fuse-overlayfs/blob/master/CHANGELOG.md
Keywords: overlayfs,fuse-overlayfs,fuse
Classifier: Programming Language :: Python :: 3
Classifier: License :: OSI Approved :: MIT License
Classifier: Operating System :: POSIX :: Linux
Requires-Python: >=3.10
License-File: LICENSE
Requires-Dist: attrs
Requires-Dist: mntfinder >=0.1.1
